{
  "rising": [
    {
      "country": "GB",
      "name": "AI Viral Video, Photo: Filter",
      "developer": "COSMOS OYUN YAZILIM DANIŞMANLIK SANAYİ TİCARET LİMİTED ŞİRKETİ",
      "prev_rank": 96,
      "curr_rank": 66,
      "delta": 30
    },
    {
      "country": "GB",
      "name": "Pro Photo Mosaic Creator",
      "developer": "Picture Mosaics LLC",
      "prev_rank": 54,
      "curr_rank": 31,
      "delta": 23
    },
    {
      "country": "FR",
      "name": "Facelab: Retouche Visage・Corps",
      "developer": "IRONTECH LIMITED",
      "prev_rank": 91,
      "curr_rank": 71,
      "delta": 20
    },
    {
      "country": "GB",
      "name": "MePic－AI Photo Video Generator",
      "developer": "Ocean Float Mobile",
      "prev_rank": 92,
      "curr_rank": 79,
      "delta": 13
    },
    {
      "country": "AU",
      "name": "Shots - AI Photo & Video Maker",
      "developer": "DeePix AI",
      "prev_rank": 97,
      "curr_rank": 84,
      "delta": 13
    },
    {
      "country": "DE",
      "name": "AI Catch: KI Video Generator",
      "developer": "Prominent Fortune PTE. LTD",
      "prev_rank": 57,
      "curr_rank": 45,
      "delta": 12
    },
    {
      "country": "GB",
      "name": "Mysticat-AI Photo Studio",
      "developer": "WUHE Technology Limited",
      "prev_rank": 56,
      "curr_rank": 46,
      "delta": 10
    },
    {
      "country": "DE",
      "name": "Pose AI | KI Bilder erstellen",
      "developer": "Spark Dynamic",
      "prev_rank": 71,
      "curr_rank": 61,
      "delta": 10
    },
    {
      "country": "ID",
      "name": "Timestamp Camera :AI Timestamp",
      "developer": "Shanghai Zongchong Information Technology Co., Ltd",
      "prev_rank": 41,
      "curr_rank": 31,
      "delta": 10
    },
    {
      "country": "AU",
      "name": "Mysticat-AI Photo Studio",
      "developer": "WUHE Technology Limited",
      "prev_rank": 47,
      "curr_rank": 37,
      "delta": 10
    }
  ],
  "by_country": {
    "GB": [
      {
        "country": "GB",
        "name": "AI Viral Video, Photo: Filter",
        "developer": "COSMOS OYUN YAZILIM DANIŞMANLIK SANAYİ TİCARET LİMİTED ŞİRKETİ",
        "prev_rank": 96,
        "curr_rank": 66,
        "delta": 30
      },
      {
        "country": "GB",
        "name": "Pro Photo Mosaic Creator",
        "developer": "Picture Mosaics LLC",
        "prev_rank": 54,
        "curr_rank": 31,
        "delta": 23
      },
      {
        "country": "GB",
        "name": "MePic－AI Photo Video Generator",
        "developer": "Ocean Float Mobile",
        "prev_rank": 92,
        "curr_rank": 79,
        "delta": 13
      },
      {
        "country": "GB",
        "name": "Mysticat-AI Photo Studio",
        "developer": "WUHE Technology Limited",
        "prev_rank": 56,
        "curr_rank": 46,
        "delta": 10
      }
    ],
    "FR": [
      {
        "country": "FR",
        "name": "Facelab: Retouche Visage・Corps",
        "developer": "IRONTECH LIMITED",
        "prev_rank": 91,
        "curr_rank": 71,
        "delta": 20
      }
    ],
    "AU": [
      {
        "country": "AU",
        "name": "Shots - AI Photo & Video Maker",
        "developer": "DeePix AI",
        "prev_rank": 97,
        "curr_rank": 84,
        "delta": 13
      },
      {
        "country": "AU",
        "name": "Mysticat-AI Photo Studio",
        "developer": "WUHE Technology Limited",
        "prev_rank": 47,
        "curr_rank": 37,
        "delta": 10
      }
    ],
    "DE": [
      {
        "country": "DE",
        "name": "AI Catch: KI Video Generator",
        "developer": "Prominent Fortune PTE. LTD",
        "prev_rank": 57,
        "curr_rank": 45,
        "delta": 12
      },
      {
        "country": "DE",
        "name": "Pose AI | KI Bilder erstellen",
        "developer": "Spark Dynamic",
        "prev_rank": 71,
        "curr_rank": 61,
        "delta": 10
      }
    ],
    "ID": [
      {
        "country": "ID",
        "name": "Timestamp Camera :AI Timestamp",
        "developer": "Shanghai Zongchong Information Technology Co., Ltd",
        "prev_rank": 41,
        "curr_rank": 31,
        "delta": 10
      }
    ]
  },
  "insights": [
    {
      "type": "trending",
      "icon": "🔥",
      "text": "AI Viral Video, Photo: Filter leads with +30 jump in GB"
    },
    {
      "type": "market",
      "icon": "🌍",
      "text": "GB has 4 rising apps - highest activity today"
    },
    {
      "type": "trending",
      "icon": "🚀",
      "text": "Mysticat-AI Photo Studio rising in 2 markets: GB, AU"
    }
  ],
  "meta": {
    "prev_date": "2026-03-08",
    "curr_date": "2026-03-09",
    "days": 1
  }
}