{
  "rising": [
    {
      "country": "BR",
      "name": "Pixelo - AI Photo Editor",
      "developer": "HAPPY TOOLS HK LIMITED",
      "prev_rank": 71,
      "curr_rank": 18,
      "delta": 53
    },
    {
      "country": "AU",
      "name": "Retake AI Face & Selfie Editor",
      "developer": "DEEP FLOW SOFTWARE SERVICES",
      "prev_rank": 100,
      "curr_rank": 49,
      "delta": 51
    },
    {
      "country": "GB",
      "name": "Dance AI: AI Dance Video Maker",
      "developer": "DeePix AI",
      "prev_rank": 83,
      "curr_rank": 37,
      "delta": 46
    },
    {
      "country": "GB",
      "name": "AgeEra - Face & Photo AI",
      "developer": "Yuenhe Innovations Co., Ltd.",
      "prev_rank": 98,
      "curr_rank": 54,
      "delta": 44
    },
    {
      "country": "US",
      "name": "Esti: Aesthetic Photo Editor",
      "developer": "Prequel Inc.",
      "prev_rank": 75,
      "curr_rank": 33,
      "delta": 42
    },
    {
      "country": "FR",
      "name": "ToonApp: Vidéo IA, Photo Anime",
      "developer": "Lyrebird Studio",
      "prev_rank": 81,
      "curr_rank": 49,
      "delta": 32
    },
    {
      "country": "JP",
      "name": "Pixi Ai：フォトマジック＆Aiビデオ",
      "developer": "INSTANOVA INNOVATION TECHNOLOGY LIMITED",
      "prev_rank": 80,
      "curr_rank": 51,
      "delta": 29
    },
    {
      "country": "KR",
      "name": "Muse: 릴스 동영상 편집 & AI",
      "developer": "Bigrowth",
      "prev_rank": 79,
      "curr_rank": 51,
      "delta": 28
    },
    {
      "country": "US",
      "name": "BeautyPlus-Selfie Photo Editor",
      "developer": "PIXOCIAL TECHNOLOGY (SINGAPORE) PTE. LTD.",
      "prev_rank": 61,
      "curr_rank": 35,
      "delta": 26
    },
    {
      "country": "US",
      "name": "Citrus 1 Tap Photo Enhancer AI",
      "developer": "Wemagine.ai LLP",
      "prev_rank": 81,
      "curr_rank": 55,
      "delta": 26
    },
    {
      "country": "IN",
      "name": "Animator - AI photo dance",
      "developer": "Shenzhen RenRenLian Technology Co., Ltd.",
      "prev_rank": 63,
      "curr_rank": 37,
      "delta": 26
    },
    {
      "country": "AU",
      "name": "BeautyPlus-Selfie Photo Editor",
      "developer": "PIXOCIAL TECHNOLOGY (SINGAPORE) PTE. LTD.",
      "prev_rank": 77,
      "curr_rank": 51,
      "delta": 26
    },
    {
      "country": "FR",
      "name": "Facelab: Retouche Visage・Corps",
      "developer": "IRONTECH LIMITED",
      "prev_rank": 97,
      "curr_rank": 73,
      "delta": 24
    },
    {
      "country": "FR",
      "name": "Photo identité - PhotoAiD",
      "developer": "Photo Aid",
      "prev_rank": 68,
      "curr_rank": 45,
      "delta": 23
    },
    {
      "country": "KR",
      "name": "Photoroom: AI 사진 편집 및 디자인",
      "developer": "Photoroom",
      "prev_rank": 69,
      "curr_rank": 46,
      "delta": 23
    },
    {
      "country": "IN",
      "name": "Flow AI - Video Generator",
      "developer": "UNIVERLIST TEKNOLOJI SANAYI VE TICARET ANONIM SIRKETI",
      "prev_rank": 52,
      "curr_rank": 29,
      "delta": 23
    },
    {
      "country": "US",
      "name": "Vixel - AI Video Generator",
      "developer": "FENIX MOBILE YAZILIM A.S.",
      "prev_rank": 93,
      "curr_rank": 71,
      "delta": 22
    },
    {
      "country": "GB",
      "name": "Retake AI: Face & Photo Editor",
      "developer": "DEEP FLOW SOFTWARE SERVICES",
      "prev_rank": 75,
      "curr_rank": 53,
      "delta": 22
    },
    {
      "country": "FR",
      "name": "PrettyUp -Retouche video corps",
      "developer": "Pixl Concerto Technology Limited",
      "prev_rank": 82,
      "curr_rank": 60,
      "delta": 22
    },
    {
      "country": "BR",
      "name": "PrettyUp-Video Portrait Editor",
      "developer": "Pixl Concerto Technology Limited",
      "prev_rank": 84,
      "curr_rank": 63,
      "delta": 21
    },
    {
      "country": "US",
      "name": "Chatlulu:Video&Photo Editor",
      "developer": "Hong Kong Endless Flow Technology Limited",
      "prev_rank": 98,
      "curr_rank": 78,
      "delta": 20
    },
    {
      "country": "US",
      "name": "FaceEra – Age & Photo AI",
      "developer": "LITTLE YELLOW DUCK TECHNOLOGY CO., LIMITED",
      "prev_rank": 63,
      "curr_rank": 44,
      "delta": 19
    },
    {
      "country": "US",
      "name": "BeautyCam-Digicam&Photo Editor",
      "developer": "Xiamen Meitu Technology Co., Ltd.",
      "prev_rank": 83,
      "curr_rank": 64,
      "delta": 19
    },
    {
      "country": "JP",
      "name": "DeeVid AI - 唯一無二のAI動画ジェネレーター",
      "developer": "ALWAYS RISING PTE. LTD.",
      "prev_rank": 99,
      "curr_rank": 80,
      "delta": 19
    },
    {
      "country": "KR",
      "name": "Hf: AI Video & Image Generator",
      "developer": "Denis Zhesterev",
      "prev_rank": 82,
      "curr_rank": 63,
      "delta": 19
    },
    {
      "country": "DE",
      "name": "Facelab・Gesicht, Körper, Haare",
      "developer": "IRONTECH LIMITED",
      "prev_rank": 69,
      "curr_rank": 51,
      "delta": 18
    },
    {
      "country": "ID",
      "name": "Muse: Reels Video Editor",
      "developer": "Bigrowth",
      "prev_rank": 48,
      "curr_rank": 30,
      "delta": 18
    },
    {
      "country": "US",
      "name": "FlashCam: AI Photo&Filter",
      "developer": "建华 董",
      "prev_rank": 77,
      "curr_rank": 61,
      "delta": 16
    },
    {
      "country": "GB",
      "name": "FaceApp: Perfect Face Editor",
      "developer": "FaceApp Technology Limited",
      "prev_rank": 31,
      "curr_rank": 16,
      "delta": 15
    },
    {
      "country": "DE",
      "name": "Mosaik+ Unschärfe Foto",
      "developer": "Shiho Sadamizu",
      "prev_rank": 84,
      "curr_rank": 69,
      "delta": 15
    },
    {
      "country": "DE",
      "name": "AI Video – KI-Video-Generator",
      "developer": "HUBX",
      "prev_rank": 85,
      "curr_rank": 70,
      "delta": 15
    },
    {
      "country": "FR",
      "name": "BeautyCam-Digicam&Photo Editor",
      "developer": "Xiamen Meitu Technology Co., Ltd.",
      "prev_rank": 58,
      "curr_rank": 44,
      "delta": 14
    },
    {
      "country": "BR",
      "name": "ToonApp: Gerador de Imagem IA",
      "developer": "Lyrebird Studio",
      "prev_rank": 60,
      "curr_rank": 46,
      "delta": 14
    },
    {
      "country": "IN",
      "name": "AI Video - AI Video Generator",
      "developer": "HUBX",
      "prev_rank": 47,
      "curr_rank": 33,
      "delta": 14
    },
    {
      "country": "ID",
      "name": "Flow AI - Video Generator",
      "developer": "UNIVERLIST TEKNOLOJI SANAYI VE TICARET ANONIM SIRKETI",
      "prev_rank": 98,
      "curr_rank": 85,
      "delta": 13
    },
    {
      "country": "AU",
      "name": "AI Video - AI Video Generator",
      "developer": "HUBX",
      "prev_rank": 34,
      "curr_rank": 21,
      "delta": 13
    },
    {
      "country": "AU",
      "name": "Instories: AI Photo & Video",
      "developer": "Ylee Studio LTD",
      "prev_rank": 70,
      "curr_rank": 57,
      "delta": 13
    },
    {
      "country": "US",
      "name": "FaceApp: Perfect Face Editor",
      "developer": "FaceApp Technology Limited",
      "prev_rank": 35,
      "curr_rank": 23,
      "delta": 12
    },
    {
      "country": "BR",
      "name": "Blow Up AI: Viralize",
      "developer": "Mountains Studio LLC",
      "prev_rank": 70,
      "curr_rank": 58,
      "delta": 12
    },
    {
      "country": "AU",
      "name": "Chatlulu:Video&Photo Editor",
      "developer": "Hong Kong Endless Flow Technology Limited",
      "prev_rank": 71,
      "curr_rank": 59,
      "delta": 12
    },
    {
      "country": "GB",
      "name": "AI Video - AI Video Generator",
      "developer": "HUBX",
      "prev_rank": 51,
      "curr_rank": 40,
      "delta": 11
    },
    {
      "country": "GB",
      "name": "BeautyPlus-Selfie Photo Editor",
      "developer": "PIXOCIAL TECHNOLOGY (SINGAPORE) PTE. LTD.",
      "prev_rank": 97,
      "curr_rank": 87,
      "delta": 10
    },
    {
      "country": "DE",
      "name": "Toonapp KI Foto Bild Generator",
      "developer": "Lyrebird Studio",
      "prev_rank": 59,
      "curr_rank": 49,
      "delta": 10
    },
    {
      "country": "DE",
      "name": "Cantina: AI Video & Characters",
      "developer": "Cantina, Inc",
      "prev_rank": 95,
      "curr_rank": 85,
      "delta": 10
    },
    {
      "country": "FR",
      "name": "Citrus 1 Tap Photo Enhancer AI",
      "developer": "Wemagine.ai LLP",
      "prev_rank": 17,
      "curr_rank": 7,
      "delta": 10
    },
    {
      "country": "FR",
      "name": "Meitu AI Photo & Video Editor",
      "developer": "Xiamen Meitu Technology Co., Ltd.",
      "prev_rank": 95,
      "curr_rank": 85,
      "delta": 10
    },
    {
      "country": "AU",
      "name": "Hypic - Photo Editor & AI Art",
      "developer": "Bytedance Pte. Ltd",
      "prev_rank": 23,
      "curr_rank": 13,
      "delta": 10
    },
    {
      "country": "AU",
      "name": "Prequel: Photo Editor, Filters",
      "developer": "Prequel Inc.",
      "prev_rank": 24,
      "curr_rank": 14,
      "delta": 10
    }
  ],
  "by_country": {
    "BR": [
      {
        "country": "BR",
        "name": "Pixelo - AI Photo Editor",
        "developer": "HAPPY TOOLS HK LIMITED",
        "prev_rank": 71,
        "curr_rank": 18,
        "delta": 53
      },
      {
        "country": "BR",
        "name": "PrettyUp-Video Portrait Editor",
        "developer": "Pixl Concerto Technology Limited",
        "prev_rank": 84,
        "curr_rank": 63,
        "delta": 21
      },
      {
        "country": "BR",
        "name": "ToonApp: Gerador de Imagem IA",
        "developer": "Lyrebird Studio",
        "prev_rank": 60,
        "curr_rank": 46,
        "delta": 14
      },
      {
        "country": "BR",
        "name": "Blow Up AI: Viralize",
        "developer": "Mountains Studio LLC",
        "prev_rank": 70,
        "curr_rank": 58,
        "delta": 12
      }
    ],
    "AU": [
      {
        "country": "AU",
        "name": "Retake AI Face & Selfie Editor",
        "developer": "DEEP FLOW SOFTWARE SERVICES",
        "prev_rank": 100,
        "curr_rank": 49,
        "delta": 51
      },
      {
        "country": "AU",
        "name": "BeautyPlus-Selfie Photo Editor",
        "developer": "PIXOCIAL TECHNOLOGY (SINGAPORE) PTE. LTD.",
        "prev_rank": 77,
        "curr_rank": 51,
        "delta": 26
      },
      {
        "country": "AU",
        "name": "AI Video - AI Video Generator",
        "developer": "HUBX",
        "prev_rank": 34,
        "curr_rank": 21,
        "delta": 13
      },
      {
        "country": "AU",
        "name": "Instories: AI Photo & Video",
        "developer": "Ylee Studio LTD",
        "prev_rank": 70,
        "curr_rank": 57,
        "delta": 13
      },
      {
        "country": "AU",
        "name": "Chatlulu:Video&Photo Editor",
        "developer": "Hong Kong Endless Flow Technology Limited",
        "prev_rank": 71,
        "curr_rank": 59,
        "delta": 12
      },
      {
        "country": "AU",
        "name": "Hypic - Photo Editor & AI Art",
        "developer": "Bytedance Pte. Ltd",
        "prev_rank": 23,
        "curr_rank": 13,
        "delta": 10
      },
      {
        "country": "AU",
        "name": "Prequel: Photo Editor, Filters",
        "developer": "Prequel Inc.",
        "prev_rank": 24,
        "curr_rank": 14,
        "delta": 10
      }
    ],
    "GB": [
      {
        "country": "GB",
        "name": "Dance AI: AI Dance Video Maker",
        "developer": "DeePix AI",
        "prev_rank": 83,
        "curr_rank": 37,
        "delta": 46
      },
      {
        "country": "GB",
        "name": "AgeEra - Face & Photo AI",
        "developer": "Yuenhe Innovations Co., Ltd.",
        "prev_rank": 98,
        "curr_rank": 54,
        "delta": 44
      },
      {
        "country": "GB",
        "name": "Retake AI: Face & Photo Editor",
        "developer": "DEEP FLOW SOFTWARE SERVICES",
        "prev_rank": 75,
        "curr_rank": 53,
        "delta": 22
      },
      {
        "country": "GB",
        "name": "FaceApp: Perfect Face Editor",
        "developer": "FaceApp Technology Limited",
        "prev_rank": 31,
        "curr_rank": 16,
        "delta": 15
      },
      {
        "country": "GB",
        "name": "AI Video - AI Video Generator",
        "developer": "HUBX",
        "prev_rank": 51,
        "curr_rank": 40,
        "delta": 11
      },
      {
        "country": "GB",
        "name": "BeautyPlus-Selfie Photo Editor",
        "developer": "PIXOCIAL TECHNOLOGY (SINGAPORE) PTE. LTD.",
        "prev_rank": 97,
        "curr_rank": 87,
        "delta": 10
      }
    ],
    "US": [
      {
        "country": "US",
        "name": "Esti: Aesthetic Photo Editor",
        "developer": "Prequel Inc.",
        "prev_rank": 75,
        "curr_rank": 33,
        "delta": 42
      },
      {
        "country": "US",
        "name": "BeautyPlus-Selfie Photo Editor",
        "developer": "PIXOCIAL TECHNOLOGY (SINGAPORE) PTE. LTD.",
        "prev_rank": 61,
        "curr_rank": 35,
        "delta": 26
      },
      {
        "country": "US",
        "name": "Citrus 1 Tap Photo Enhancer AI",
        "developer": "Wemagine.ai LLP",
        "prev_rank": 81,
        "curr_rank": 55,
        "delta": 26
      },
      {
        "country": "US",
        "name": "Vixel - AI Video Generator",
        "developer": "FENIX MOBILE YAZILIM A.S.",
        "prev_rank": 93,
        "curr_rank": 71,
        "delta": 22
      },
      {
        "country": "US",
        "name": "Chatlulu:Video&Photo Editor",
        "developer": "Hong Kong Endless Flow Technology Limited",
        "prev_rank": 98,
        "curr_rank": 78,
        "delta": 20
      },
      {
        "country": "US",
        "name": "FaceEra – Age & Photo AI",
        "developer": "LITTLE YELLOW DUCK TECHNOLOGY CO., LIMITED",
        "prev_rank": 63,
        "curr_rank": 44,
        "delta": 19
      },
      {
        "country": "US",
        "name": "BeautyCam-Digicam&Photo Editor",
        "developer": "Xiamen Meitu Technology Co., Ltd.",
        "prev_rank": 83,
        "curr_rank": 64,
        "delta": 19
      },
      {
        "country": "US",
        "name": "FlashCam: AI Photo&Filter",
        "developer": "建华 董",
        "prev_rank": 77,
        "curr_rank": 61,
        "delta": 16
      },
      {
        "country": "US",
        "name": "FaceApp: Perfect Face Editor",
        "developer": "FaceApp Technology Limited",
        "prev_rank": 35,
        "curr_rank": 23,
        "delta": 12
      }
    ],
    "FR": [
      {
        "country": "FR",
        "name": "ToonApp: Vidéo IA, Photo Anime",
        "developer": "Lyrebird Studio",
        "prev_rank": 81,
        "curr_rank": 49,
        "delta": 32
      },
      {
        "country": "FR",
        "name": "Facelab: Retouche Visage・Corps",
        "developer": "IRONTECH LIMITED",
        "prev_rank": 97,
        "curr_rank": 73,
        "delta": 24
      },
      {
        "country": "FR",
        "name": "Photo identité - PhotoAiD",
        "developer": "Photo Aid",
        "prev_rank": 68,
        "curr_rank": 45,
        "delta": 23
      },
      {
        "country": "FR",
        "name": "PrettyUp -Retouche video corps",
        "developer": "Pixl Concerto Technology Limited",
        "prev_rank": 82,
        "curr_rank": 60,
        "delta": 22
      },
      {
        "country": "FR",
        "name": "BeautyCam-Digicam&Photo Editor",
        "developer": "Xiamen Meitu Technology Co., Ltd.",
        "prev_rank": 58,
        "curr_rank": 44,
        "delta": 14
      },
      {
        "country": "FR",
        "name": "Citrus 1 Tap Photo Enhancer AI",
        "developer": "Wemagine.ai LLP",
        "prev_rank": 17,
        "curr_rank": 7,
        "delta": 10
      },
      {
        "country": "FR",
        "name": "Meitu AI Photo & Video Editor",
        "developer": "Xiamen Meitu Technology Co., Ltd.",
        "prev_rank": 95,
        "curr_rank": 85,
        "delta": 10
      }
    ],
    "JP": [
      {
        "country": "JP",
        "name": "Pixi Ai：フォトマジック＆Aiビデオ",
        "developer": "INSTANOVA INNOVATION TECHNOLOGY LIMITED",
        "prev_rank": 80,
        "curr_rank": 51,
        "delta": 29
      },
      {
        "country": "JP",
        "name": "DeeVid AI - 唯一無二のAI動画ジェネレーター",
        "developer": "ALWAYS RISING PTE. LTD.",
        "prev_rank": 99,
        "curr_rank": 80,
        "delta": 19
      }
    ],
    "KR": [
      {
        "country": "KR",
        "name": "Muse: 릴스 동영상 편집 & AI",
        "developer": "Bigrowth",
        "prev_rank": 79,
        "curr_rank": 51,
        "delta": 28
      },
      {
        "country": "KR",
        "name": "Photoroom: AI 사진 편집 및 디자인",
        "developer": "Photoroom",
        "prev_rank": 69,
        "curr_rank": 46,
        "delta": 23
      },
      {
        "country": "KR",
        "name": "Hf: AI Video & Image Generator",
        "developer": "Denis Zhesterev",
        "prev_rank": 82,
        "curr_rank": 63,
        "delta": 19
      }
    ],
    "IN": [
      {
        "country": "IN",
        "name": "Animator - AI photo dance",
        "developer": "Shenzhen RenRenLian Technology Co., Ltd.",
        "prev_rank": 63,
        "curr_rank": 37,
        "delta": 26
      },
      {
        "country": "IN",
        "name": "Flow AI - Video Generator",
        "developer": "UNIVERLIST TEKNOLOJI SANAYI VE TICARET ANONIM SIRKETI",
        "prev_rank": 52,
        "curr_rank": 29,
        "delta": 23
      },
      {
        "country": "IN",
        "name": "AI Video - AI Video Generator",
        "developer": "HUBX",
        "prev_rank": 47,
        "curr_rank": 33,
        "delta": 14
      }
    ],
    "DE": [
      {
        "country": "DE",
        "name": "Facelab・Gesicht, Körper, Haare",
        "developer": "IRONTECH LIMITED",
        "prev_rank": 69,
        "curr_rank": 51,
        "delta": 18
      },
      {
        "country": "DE",
        "name": "Mosaik+ Unschärfe Foto",
        "developer": "Shiho Sadamizu",
        "prev_rank": 84,
        "curr_rank": 69,
        "delta": 15
      },
      {
        "country": "DE",
        "name": "AI Video – KI-Video-Generator",
        "developer": "HUBX",
        "prev_rank": 85,
        "curr_rank": 70,
        "delta": 15
      },
      {
        "country": "DE",
        "name": "Toonapp KI Foto Bild Generator",
        "developer": "Lyrebird Studio",
        "prev_rank": 59,
        "curr_rank": 49,
        "delta": 10
      },
      {
        "country": "DE",
        "name": "Cantina: AI Video & Characters",
        "developer": "Cantina, Inc",
        "prev_rank": 95,
        "curr_rank": 85,
        "delta": 10
      }
    ],
    "ID": [
      {
        "country": "ID",
        "name": "Muse: Reels Video Editor",
        "developer": "Bigrowth",
        "prev_rank": 48,
        "curr_rank": 30,
        "delta": 18
      },
      {
        "country": "ID",
        "name": "Flow AI - Video Generator",
        "developer": "UNIVERLIST TEKNOLOJI SANAYI VE TICARET ANONIM SIRKETI",
        "prev_rank": 98,
        "curr_rank": 85,
        "delta": 13
      }
    ]
  },
  "insights": [
    {
      "type": "trending",
      "icon": "🔥",
      "text": "Pixelo - AI Photo Editor leads with +53 jump in BR"
    },
    {
      "type": "market",
      "icon": "🌍",
      "text": "US has 9 rising apps - highest activity today"
    },
    {
      "type": "app-note",
      "icon": "📱",
      "text": "FaceLab apps trending with 2 variants rising"
    },
    {
      "type": "trending",
      "icon": "🚀",
      "text": "BeautyPlus-Selfie Photo Editor rising in 3 markets: US, AU, GB"
    }
  ],
  "meta": {
    "prev_date": "2026-06-26",
    "curr_date": "2026-07-03",
    "days": 7
  }
}