{
  "rising": [
    {
      "country": "US",
      "name": "AI Catch: AI Video Generator",
      "developer": "Prominent Fortune PTE. LTD",
      "prev_rank": 90,
      "curr_rank": 18,
      "delta": 72
    },
    {
      "country": "GB",
      "name": "AI Catch: AI Video Generator",
      "developer": "Prominent Fortune PTE. LTD",
      "prev_rank": 100,
      "curr_rank": 38,
      "delta": 62
    },
    {
      "country": "FR",
      "name": "AI Catch: AI Video Generator",
      "developer": "Prominent Fortune PTE. LTD",
      "prev_rank": 80,
      "curr_rank": 18,
      "delta": 62
    },
    {
      "country": "AU",
      "name": "AI Catch: AI Video Generator",
      "developer": "Prominent Fortune PTE. LTD",
      "prev_rank": 94,
      "curr_rank": 32,
      "delta": 62
    },
    {
      "country": "IN",
      "name": "HairX AI, Hairstyle Try On Cut",
      "developer": "小舟 陈",
      "prev_rank": 76,
      "curr_rank": 15,
      "delta": 61
    },
    {
      "country": "ID",
      "name": "AI Catch: AI Video Generator",
      "developer": "Prominent Fortune PTE. LTD",
      "prev_rank": 95,
      "curr_rank": 51,
      "delta": 44
    },
    {
      "country": "DE",
      "name": "AI Catch: KI Video Generator",
      "developer": "Prominent Fortune PTE. LTD",
      "prev_rank": 56,
      "curr_rank": 17,
      "delta": 39
    },
    {
      "country": "DE",
      "name": "AI Mirror: Gesichtsfoto-Editor",
      "developer": "POLYVERSE ENTERTAINMENT INC.",
      "prev_rank": 82,
      "curr_rank": 43,
      "delta": 39
    },
    {
      "country": "GB",
      "name": "Captions: AI Edits Your Video",
      "developer": "Captions, LLC (US)",
      "prev_rank": 70,
      "curr_rank": 34,
      "delta": 36
    },
    {
      "country": "AU",
      "name": "Chatlulu- Video & Photo Editor",
      "developer": "Hong Kong Endless Flow Technology Limited",
      "prev_rank": 98,
      "curr_rank": 63,
      "delta": 35
    },
    {
      "country": "KR",
      "name": "Filmora: AI 영상 제작 & 동영상 편집",
      "developer": "Shenzhen Wondershare Software Co., Ltd",
      "prev_rank": 98,
      "curr_rank": 64,
      "delta": 34
    },
    {
      "country": "FR",
      "name": "AI Mirror: Éditeur de visage",
      "developer": "POLYVERSE ENTERTAINMENT INC.",
      "prev_rank": 81,
      "curr_rank": 48,
      "delta": 33
    },
    {
      "country": "BR",
      "name": "AI Catch: IA Vídeo Gerador",
      "developer": "Prominent Fortune PTE. LTD",
      "prev_rank": 42,
      "curr_rank": 10,
      "delta": 32
    },
    {
      "country": "GB",
      "name": "AI Mirror: AI Photo Editor",
      "developer": "POLYVERSE ENTERTAINMENT INC.",
      "prev_rank": 77,
      "curr_rank": 46,
      "delta": 31
    },
    {
      "country": "AU",
      "name": "AI Mirror: AI Photo Editor",
      "developer": "POLYVERSE ENTERTAINMENT INC.",
      "prev_rank": 80,
      "curr_rank": 54,
      "delta": 26
    },
    {
      "country": "US",
      "name": "Airbrush: Face Photo Editor",
      "developer": "PIXOCIAL TECHNOLOGY (SINGAPORE) PTE. LTD.",
      "prev_rank": 44,
      "curr_rank": 19,
      "delta": 25
    },
    {
      "country": "GB",
      "name": "AI Photo Video Editor, Enhance",
      "developer": "COOL SUMMER LIMITED",
      "prev_rank": 84,
      "curr_rank": 59,
      "delta": 25
    },
    {
      "country": "IN",
      "name": "AI LOOK: Photo to Video AI",
      "developer": "Bao Teng Technology Limited",
      "prev_rank": 89,
      "curr_rank": 64,
      "delta": 25
    },
    {
      "country": "DE",
      "name": "ARTA: KI-Bild-Generator",
      "developer": "AIBY",
      "prev_rank": 80,
      "curr_rank": 56,
      "delta": 24
    },
    {
      "country": "DE",
      "name": "Vids AI - Reels Video Editor",
      "developer": "Viral Vision Ltd.",
      "prev_rank": 75,
      "curr_rank": 52,
      "delta": 23
    },
    {
      "country": "AU",
      "name": "Pose: AI Photo Video Generator",
      "developer": "Spark Dynamic",
      "prev_rank": 38,
      "curr_rank": 17,
      "delta": 21
    },
    {
      "country": "KR",
      "name": "Hypic - Photo Editor & AI Art",
      "developer": "Bytedance Pte. Ltd",
      "prev_rank": 47,
      "curr_rank": 27,
      "delta": 20
    },
    {
      "country": "GB",
      "name": "Splice - Video Editor & Maker",
      "developer": "Bending Spoons Apps ApS",
      "prev_rank": 82,
      "curr_rank": 63,
      "delta": 19
    },
    {
      "country": "AU",
      "name": "Captions: AI Edits Your Video",
      "developer": "Captions, LLC (US)",
      "prev_rank": 59,
      "curr_rank": 40,
      "delta": 19
    },
    {
      "country": "AU",
      "name": "Instories: AI Photo & Video",
      "developer": "Ylee Studio LTD",
      "prev_rank": 66,
      "curr_rank": 47,
      "delta": 19
    },
    {
      "country": "AU",
      "name": "Facelab: Face & Body Editor",
      "developer": "IRONTECH LIMITED",
      "prev_rank": 92,
      "curr_rank": 74,
      "delta": 18
    },
    {
      "country": "KR",
      "name": "Adobe Premiere AI 비디오 에디터",
      "developer": "Adobe Inc.",
      "prev_rank": 75,
      "curr_rank": 58,
      "delta": 17
    },
    {
      "country": "GB",
      "name": "Meitu- AI Photo & Video Editor",
      "developer": "Xiamen Meitu Technology Co., Ltd.",
      "prev_rank": 80,
      "curr_rank": 64,
      "delta": 16
    },
    {
      "country": "DE",
      "name": "AI Foto - Editor, Verbesserer",
      "developer": "COOL SUMMER LIMITED",
      "prev_rank": 65,
      "curr_rank": 49,
      "delta": 16
    },
    {
      "country": "DE",
      "name": "Mosaik+ Unschärfe Foto",
      "developer": "Shiho Sadamizu",
      "prev_rank": 71,
      "curr_rank": 55,
      "delta": 16
    },
    {
      "country": "IN",
      "name": "Muse: Reels Video Editor",
      "developer": "Bigrowth",
      "prev_rank": 67,
      "curr_rank": 51,
      "delta": 16
    },
    {
      "country": "US",
      "name": "Adobe Premiere AI Video Editor",
      "developer": "Adobe Inc.",
      "prev_rank": 43,
      "curr_rank": 28,
      "delta": 15
    },
    {
      "country": "US",
      "name": "Citrus 1 Tap Photo Enhancer AI",
      "developer": "Wemagine.ai LLP",
      "prev_rank": 57,
      "curr_rank": 42,
      "delta": 15
    },
    {
      "country": "FR",
      "name": "Meitu- AI Photo & Video Editor",
      "developer": "Xiamen Meitu Technology Co., Ltd.",
      "prev_rank": 92,
      "curr_rank": 77,
      "delta": 15
    },
    {
      "country": "BR",
      "name": "Facelab - Editor de Fotos IA",
      "developer": "IRONTECH LIMITED",
      "prev_rank": 96,
      "curr_rank": 81,
      "delta": 15
    },
    {
      "country": "AU",
      "name": "Muse Reel Maker & Video Editor",
      "developer": "Bigrowth",
      "prev_rank": 53,
      "curr_rank": 39,
      "delta": 14
    },
    {
      "country": "IN",
      "name": "Filmora：AI Video Editor, Maker",
      "developer": "Shenzhen Wondershare Software Co., Ltd",
      "prev_rank": 35,
      "curr_rank": 22,
      "delta": 13
    },
    {
      "country": "US",
      "name": "Prequel: Photo & Video Editor",
      "developer": "Prequel Inc.",
      "prev_rank": 65,
      "curr_rank": 53,
      "delta": 12
    },
    {
      "country": "GB",
      "name": "Blur Photo & Mosaic",
      "developer": "Yu Abe",
      "prev_rank": 94,
      "curr_rank": 82,
      "delta": 12
    },
    {
      "country": "BR",
      "name": "AI Mirror: Fotos anime IA",
      "developer": "POLYVERSE ENTERTAINMENT INC.",
      "prev_rank": 41,
      "curr_rank": 29,
      "delta": 12
    },
    {
      "country": "IN",
      "name": "invideo AI: AI Video Generator",
      "developer": "Invideo Inc",
      "prev_rank": 54,
      "curr_rank": 42,
      "delta": 12
    },
    {
      "country": "GB",
      "name": "Facetune: Video & Photo Editor",
      "developer": "Lightricks Ltd.",
      "prev_rank": 33,
      "curr_rank": 22,
      "delta": 11
    },
    {
      "country": "KR",
      "name": "AIReel：AI 영상&사진 편집",
      "developer": "Zhao Yali",
      "prev_rank": 40,
      "curr_rank": 29,
      "delta": 11
    },
    {
      "country": "ID",
      "name": "EPIK - AI Photo & Video Editor",
      "developer": "SNOW Corporation",
      "prev_rank": 80,
      "curr_rank": 69,
      "delta": 11
    },
    {
      "country": "GB",
      "name": "Adobe Premiere AI Video Editor",
      "developer": "Adobe Inc.",
      "prev_rank": 39,
      "curr_rank": 29,
      "delta": 10
    },
    {
      "country": "FR",
      "name": "Pose : IA Photo, Image & Vidéo",
      "developer": "Spark Dynamic",
      "prev_rank": 49,
      "curr_rank": 39,
      "delta": 10
    },
    {
      "country": "IN",
      "name": "AI Video - AI Video Generator",
      "developer": "HUBX",
      "prev_rank": 84,
      "curr_rank": 74,
      "delta": 10
    },
    {
      "country": "IN",
      "name": "VSCO: Photo Editor",
      "developer": "Visual Supply Company",
      "prev_rank": 88,
      "curr_rank": 78,
      "delta": 10
    }
  ],
  "by_country": {
    "US": [
      {
        "country": "US",
        "name": "AI Catch: AI Video Generator",
        "developer": "Prominent Fortune PTE. LTD",
        "prev_rank": 90,
        "curr_rank": 18,
        "delta": 72
      },
      {
        "country": "US",
        "name": "Airbrush: Face Photo Editor",
        "developer": "PIXOCIAL TECHNOLOGY (SINGAPORE) PTE. LTD.",
        "prev_rank": 44,
        "curr_rank": 19,
        "delta": 25
      },
      {
        "country": "US",
        "name": "Adobe Premiere AI Video Editor",
        "developer": "Adobe Inc.",
        "prev_rank": 43,
        "curr_rank": 28,
        "delta": 15
      },
      {
        "country": "US",
        "name": "Citrus 1 Tap Photo Enhancer AI",
        "developer": "Wemagine.ai LLP",
        "prev_rank": 57,
        "curr_rank": 42,
        "delta": 15
      },
      {
        "country": "US",
        "name": "Prequel: Photo & Video Editor",
        "developer": "Prequel Inc.",
        "prev_rank": 65,
        "curr_rank": 53,
        "delta": 12
      }
    ],
    "GB": [
      {
        "country": "GB",
        "name": "AI Catch: AI Video Generator",
        "developer": "Prominent Fortune PTE. LTD",
        "prev_rank": 100,
        "curr_rank": 38,
        "delta": 62
      },
      {
        "country": "GB",
        "name": "Captions: AI Edits Your Video",
        "developer": "Captions, LLC (US)",
        "prev_rank": 70,
        "curr_rank": 34,
        "delta": 36
      },
      {
        "country": "GB",
        "name": "AI Mirror: AI Photo Editor",
        "developer": "POLYVERSE ENTERTAINMENT INC.",
        "prev_rank": 77,
        "curr_rank": 46,
        "delta": 31
      },
      {
        "country": "GB",
        "name": "AI Photo Video Editor, Enhance",
        "developer": "COOL SUMMER LIMITED",
        "prev_rank": 84,
        "curr_rank": 59,
        "delta": 25
      },
      {
        "country": "GB",
        "name": "Splice - Video Editor & Maker",
        "developer": "Bending Spoons Apps ApS",
        "prev_rank": 82,
        "curr_rank": 63,
        "delta": 19
      },
      {
        "country": "GB",
        "name": "Meitu- AI Photo & Video Editor",
        "developer": "Xiamen Meitu Technology Co., Ltd.",
        "prev_rank": 80,
        "curr_rank": 64,
        "delta": 16
      },
      {
        "country": "GB",
        "name": "Blur Photo & Mosaic",
        "developer": "Yu Abe",
        "prev_rank": 94,
        "curr_rank": 82,
        "delta": 12
      },
      {
        "country": "GB",
        "name": "Facetune: Video & Photo Editor",
        "developer": "Lightricks Ltd.",
        "prev_rank": 33,
        "curr_rank": 22,
        "delta": 11
      },
      {
        "country": "GB",
        "name": "Adobe Premiere AI Video Editor",
        "developer": "Adobe Inc.",
        "prev_rank": 39,
        "curr_rank": 29,
        "delta": 10
      }
    ],
    "FR": [
      {
        "country": "FR",
        "name": "AI Catch: AI Video Generator",
        "developer": "Prominent Fortune PTE. LTD",
        "prev_rank": 80,
        "curr_rank": 18,
        "delta": 62
      },
      {
        "country": "FR",
        "name": "AI Mirror: Éditeur de visage",
        "developer": "POLYVERSE ENTERTAINMENT INC.",
        "prev_rank": 81,
        "curr_rank": 48,
        "delta": 33
      },
      {
        "country": "FR",
        "name": "Meitu- AI Photo & Video Editor",
        "developer": "Xiamen Meitu Technology Co., Ltd.",
        "prev_rank": 92,
        "curr_rank": 77,
        "delta": 15
      },
      {
        "country": "FR",
        "name": "Pose : IA Photo, Image & Vidéo",
        "developer": "Spark Dynamic",
        "prev_rank": 49,
        "curr_rank": 39,
        "delta": 10
      }
    ],
    "AU": [
      {
        "country": "AU",
        "name": "AI Catch: AI Video Generator",
        "developer": "Prominent Fortune PTE. LTD",
        "prev_rank": 94,
        "curr_rank": 32,
        "delta": 62
      },
      {
        "country": "AU",
        "name": "Chatlulu- Video & Photo Editor",
        "developer": "Hong Kong Endless Flow Technology Limited",
        "prev_rank": 98,
        "curr_rank": 63,
        "delta": 35
      },
      {
        "country": "AU",
        "name": "AI Mirror: AI Photo Editor",
        "developer": "POLYVERSE ENTERTAINMENT INC.",
        "prev_rank": 80,
        "curr_rank": 54,
        "delta": 26
      },
      {
        "country": "AU",
        "name": "Pose: AI Photo Video Generator",
        "developer": "Spark Dynamic",
        "prev_rank": 38,
        "curr_rank": 17,
        "delta": 21
      },
      {
        "country": "AU",
        "name": "Captions: AI Edits Your Video",
        "developer": "Captions, LLC (US)",
        "prev_rank": 59,
        "curr_rank": 40,
        "delta": 19
      },
      {
        "country": "AU",
        "name": "Instories: AI Photo & Video",
        "developer": "Ylee Studio LTD",
        "prev_rank": 66,
        "curr_rank": 47,
        "delta": 19
      },
      {
        "country": "AU",
        "name": "Facelab: Face & Body Editor",
        "developer": "IRONTECH LIMITED",
        "prev_rank": 92,
        "curr_rank": 74,
        "delta": 18
      },
      {
        "country": "AU",
        "name": "Muse Reel Maker & Video Editor",
        "developer": "Bigrowth",
        "prev_rank": 53,
        "curr_rank": 39,
        "delta": 14
      }
    ],
    "IN": [
      {
        "country": "IN",
        "name": "HairX AI, Hairstyle Try On Cut",
        "developer": "小舟 陈",
        "prev_rank": 76,
        "curr_rank": 15,
        "delta": 61
      },
      {
        "country": "IN",
        "name": "AI LOOK: Photo to Video AI",
        "developer": "Bao Teng Technology Limited",
        "prev_rank": 89,
        "curr_rank": 64,
        "delta": 25
      },
      {
        "country": "IN",
        "name": "Muse: Reels Video Editor",
        "developer": "Bigrowth",
        "prev_rank": 67,
        "curr_rank": 51,
        "delta": 16
      },
      {
        "country": "IN",
        "name": "Filmora：AI Video Editor, Maker",
        "developer": "Shenzhen Wondershare Software Co., Ltd",
        "prev_rank": 35,
        "curr_rank": 22,
        "delta": 13
      },
      {
        "country": "IN",
        "name": "invideo AI: AI Video Generator",
        "developer": "Invideo Inc",
        "prev_rank": 54,
        "curr_rank": 42,
        "delta": 12
      },
      {
        "country": "IN",
        "name": "AI Video - AI Video Generator",
        "developer": "HUBX",
        "prev_rank": 84,
        "curr_rank": 74,
        "delta": 10
      },
      {
        "country": "IN",
        "name": "VSCO: Photo Editor",
        "developer": "Visual Supply Company",
        "prev_rank": 88,
        "curr_rank": 78,
        "delta": 10
      }
    ],
    "ID": [
      {
        "country": "ID",
        "name": "AI Catch: AI Video Generator",
        "developer": "Prominent Fortune PTE. LTD",
        "prev_rank": 95,
        "curr_rank": 51,
        "delta": 44
      },
      {
        "country": "ID",
        "name": "EPIK - AI Photo & Video Editor",
        "developer": "SNOW Corporation",
        "prev_rank": 80,
        "curr_rank": 69,
        "delta": 11
      }
    ],
    "DE": [
      {
        "country": "DE",
        "name": "AI Catch: KI Video Generator",
        "developer": "Prominent Fortune PTE. LTD",
        "prev_rank": 56,
        "curr_rank": 17,
        "delta": 39
      },
      {
        "country": "DE",
        "name": "AI Mirror: Gesichtsfoto-Editor",
        "developer": "POLYVERSE ENTERTAINMENT INC.",
        "prev_rank": 82,
        "curr_rank": 43,
        "delta": 39
      },
      {
        "country": "DE",
        "name": "ARTA: KI-Bild-Generator",
        "developer": "AIBY",
        "prev_rank": 80,
        "curr_rank": 56,
        "delta": 24
      },
      {
        "country": "DE",
        "name": "Vids AI - Reels Video Editor",
        "developer": "Viral Vision Ltd.",
        "prev_rank": 75,
        "curr_rank": 52,
        "delta": 23
      },
      {
        "country": "DE",
        "name": "AI Foto - Editor, Verbesserer",
        "developer": "COOL SUMMER LIMITED",
        "prev_rank": 65,
        "curr_rank": 49,
        "delta": 16
      },
      {
        "country": "DE",
        "name": "Mosaik+ Unschärfe Foto",
        "developer": "Shiho Sadamizu",
        "prev_rank": 71,
        "curr_rank": 55,
        "delta": 16
      }
    ],
    "KR": [
      {
        "country": "KR",
        "name": "Filmora: AI 영상 제작 & 동영상 편집",
        "developer": "Shenzhen Wondershare Software Co., Ltd",
        "prev_rank": 98,
        "curr_rank": 64,
        "delta": 34
      },
      {
        "country": "KR",
        "name": "Hypic - Photo Editor & AI Art",
        "developer": "Bytedance Pte. Ltd",
        "prev_rank": 47,
        "curr_rank": 27,
        "delta": 20
      },
      {
        "country": "KR",
        "name": "Adobe Premiere AI 비디오 에디터",
        "developer": "Adobe Inc.",
        "prev_rank": 75,
        "curr_rank": 58,
        "delta": 17
      },
      {
        "country": "KR",
        "name": "AIReel：AI 영상&사진 편집",
        "developer": "Zhao Yali",
        "prev_rank": 40,
        "curr_rank": 29,
        "delta": 11
      }
    ],
    "BR": [
      {
        "country": "BR",
        "name": "AI Catch: IA Vídeo Gerador",
        "developer": "Prominent Fortune PTE. LTD",
        "prev_rank": 42,
        "curr_rank": 10,
        "delta": 32
      },
      {
        "country": "BR",
        "name": "Facelab - Editor de Fotos IA",
        "developer": "IRONTECH LIMITED",
        "prev_rank": 96,
        "curr_rank": 81,
        "delta": 15
      },
      {
        "country": "BR",
        "name": "AI Mirror: Fotos anime IA",
        "developer": "POLYVERSE ENTERTAINMENT INC.",
        "prev_rank": 41,
        "curr_rank": 29,
        "delta": 12
      }
    ]
  },
  "insights": [
    {
      "type": "trending",
      "icon": "🔥",
      "text": "AI Catch: AI Video Generator leads with +72 jump in US"
    },
    {
      "type": "market",
      "icon": "🌍",
      "text": "GB has 9 rising apps - highest activity today"
    },
    {
      "type": "app-note",
      "icon": "📱",
      "text": "AI Catch apps trending with 7 variants rising"
    },
    {
      "type": "trending",
      "icon": "🚀",
      "text": "AI Catch: AI Video Generator rising in 5 markets: US, GB, FR, AU, ID"
    }
  ],
  "meta": {
    "prev_date": "2026-04-18",
    "curr_date": "2026-04-25",
    "days": 7
  }
}